{
  "project_info": {
    "project_number": "343049705100",
    "project_id": "mindriserecommerceapp",
    "storage_bucket": "mindriserecommerceapp.firebasestorage.app"
  },
  "client": [
    {
      "client_info": {
        "mobilesdk_app_id": "1:343049705100:android:88a09f0616963782440da9",
        "android_client_info": {
          "package_name": "com.example.flutterecommerceapp"
        }
      },
      "oauth_client": [],
      "api_key": [
        {
          "current_key": "AIzaSyBG-W9RrL8rrPIKiEXXuKoFWasBhxozOH8"
        }
      ],
      "services": {
        "appinvite_service": {
          "other_platform_oauth_client": []
        }
      }
    }
  ],
  "configuration_version": "1"
}